mcp_tool_override_tester/main.py
mcp_tool_override_tester-0.1.1.dist-info/METADATA
mcp_tool_override_tester-0.1.1.dist-info/WHEEL
mcp_tool_override_tester-0.1.1.dist-info/entry_points.txt
mcp_tool_override_tester-0.1.1.dist-info/top_level.txt
mcp_tool_override_tester-0.1.1.dist-info/RECORD
