Metadata-Version: 2.4
Name: mcp_tool_override_tester
Version: 0.1.1
Summary: Verifies if a tool with the same name can override an existing one on a different server.
Author-email: Jingu Kang <jingu.zhenqiu.kang@gmail.com>
License: MIT
Requires-Python: >=3.10
Requires-Dist: mcp[cli]>=1.6.0
